<?xml version="1.0" encoding="UTF-8"?>
<dataSet authors="Roberto Navigli, Daniele Vannella" task="SemeVal 2013 task 11" lang="en">
  <match_point.n.test>
    <match_point.n.1 url="http://www.imdb.com/title/tt0416320/" title="Match Point (2005) - IMDb">
      <TargetSentence>Directed by Woody Allen. With Scarlett Johansson, Jonathan Rhys Meyers, Emily   Mortimer, Matthew Goode. At a turning point in his life, a former tennis pro falls &lt;b&gt;...&lt;/b&gt;</TargetSentence>
    </match_point.n.1>
    <match_point.n.2 url="http://en.wikipedia.org/wiki/Match_Point" title="Match Point - Wikipedia, the free encyclopedia">
      <TargetSentence>&lt;b&gt;Match Point&lt;/b&gt; is a 2005 dramatic-thriller film written and directed by Woody Allen   which stars Jonathan Rhys Meyers, Scarlett Johansson, Emily Mortimer, Matthew &lt;b&gt;...&lt;/b&gt;</TargetSentence>
    </match_point.n.2>
    <match_point.n.3 url="http://www.youtube.com/watch%3Fv%3D_xegPAYN7HU" title="Match Point - Trailer (Ponto Final) - Woody Allen - YouTube">
      <TargetSentence>Nov 7, 2006 &lt;b&gt;...&lt;/b&gt; Sign in with your YouTube Account (YouTube, Google+, Gmail, Orkut, Picasa, or   Chrome) to add CaioDelcolli&amp;#39;s video to your playlist. Sign in &lt;b&gt;...&lt;/b&gt;</TargetSentence>
    </match_point.n.3>
    <match_point.n.4 url="http://www.rottentomatoes.com/m/match_point/" title="Match Point - Rotten Tomatoes">
      <TargetSentence>Review: Woody Allen&amp;#39;s sharpest film in years, &lt;b&gt;Match Point&lt;/b&gt; is a taut, philosophical   thriller about class and infidelity.</TargetSentence>
    </match_point.n.4>
    <match_point.n.5 url="http://www.amazon.com/Match-Point-Scarlett-Johansson/dp/B000EQHXNW" title="Amazon.com: Match Point: Scarlett Johansson, Jonathan Rhys ...">
      <TargetSentence>The passion of mad love and the cold calculations of social climbing collide in   Woody Allen&amp;#39;s &lt;b&gt;Match Point&lt;/b&gt;. Former tennis pro Chris Wilton (Jonathan &lt;b&gt;...&lt;/b&gt;</TargetSentence>
    </match_point.n.5>
    <match_point.n.6 url="http://trailers.apple.com/trailers/dreamworks/match_point/" title="Match Point - Movie Trailers - iTunes">
      <TargetSentence>A drama about ambition, the seduction of wealth, love, and sexual passion.   Perhaps most importantly, however, the story reveals the huge part luck plays in &lt;b&gt;...&lt;/b&gt;</TargetSentence>
    </match_point.n.6>
    <match_point.n.7 url="http://www.thefreedictionary.com/match%2Bpoint" title="match point - definition of match point by the Free Online Dictionary ...">
      <TargetSentence>The final point needed to win a sports match, especially in tennis. &lt;b&gt;match point&lt;/b&gt;. n.   1. (General Sporting Terms) Sport the final point needed to win a match. 2.</TargetSentence>
    </match_point.n.7>
    <match_point.n.8 url="http://www.matchpoint.dreamworks.com/" title="Match Point - DreamWorks Animation">
      <TargetSentence />
    </match_point.n.8>
    <match_point.n.9 url="http://trailers.apple.com/trailers/dreamworks/match_point/trailer/" title="Apple - Trailers - Match Point - Trailer">
      <TargetSentence>A drama about ambition, the seduction of wealth, love, and sexual passion.   Perhaps most importantly, however, the story reveals the huge part luck plays in &lt;b&gt;...&lt;/b&gt;</TargetSentence>
    </match_point.n.9>
    <match_point.n.10 url="http://movies.yahoo.com/movie/match-point/" title="Match Point | Trailer and Cast - Yahoo! Movies">
      <TargetSentence>Get the complete cast, production details, reviews and trailer of &lt;b&gt;Match Point&lt;/b&gt; on   Yahoo! Movies. A one-time tennis pro, Chris Wilton was used to falling just short &lt;b&gt;...&lt;/b&gt;</TargetSentence>
    </match_point.n.10>
    <match_point.n.11 url="http://www.rogerebert.com/apps/pbcs.dll/article%3FAID%3D/20060105/REVIEWS/60103004/1023" title="Match Point :: rogerebert.com :: Reviews">
      <TargetSentence>Jan 6, 2006 &lt;b&gt;...&lt;/b&gt; One reason for the fascination of Woody Allen&amp;#39;s &amp;quot;&lt;b&gt;Match Point&lt;/b&gt;&amp;quot; is that each and   every character is rotten. This is a thriller not about good versus &lt;b&gt;...&lt;/b&gt;</TargetSentence>
    </match_point.n.11>
    <match_point.n.12 url="http://www.mppartnersllc.com/" title="Match Point Partners">
      <TargetSentence>&lt;b&gt;Match Point&lt;/b&gt; Partners is an advisory firm providing a unique blend of value-added   strategic, operating and investment banking services to emerging middle &lt;b&gt;...&lt;/b&gt;</TargetSentence>
    </match_point.n.12>
    <match_point.n.13 url="http://www.linkedin.com/company/match-point-partners" title="Match Point Partners | LinkedIn">
      <TargetSentence>Welcome to the company profile of &lt;b&gt;Match Point&lt;/b&gt; Partners on LinkedIn. &lt;b&gt;Match Point&lt;/b&gt;   Partners is a trusted advisor to companies and investors in the healthcare and.</TargetSentence>
    </match_point.n.13>
    <match_point.n.14 url="http://en.wikiquote.org/wiki/Match_Point" title="Match Point - Wikiquote">
      <TargetSentence>&lt;b&gt;Match Point&lt;/b&gt; is a 2005 film about a former tennis pro, Chris Wilton, who falls for a   beautiful woman who turns out to be his friend&amp;#39;s fiancee and soon-to-be &lt;b&gt;...&lt;/b&gt;</TargetSentence>
    </match_point.n.14>
    <match_point.n.15 url="http://movies.nytimes.com/movie/326909/Match-Point/overview" title="Match-Point - Trailer - Cast - Showtimes - NYTimes.com">
      <TargetSentence>An overview of &lt;b&gt;Match Point&lt;/b&gt;, including cast and credit details, a review summary,   and more.</TargetSentence>
    </match_point.n.15>
    <match_point.n.16 url="http://products.daltile.com/series.cfm%3Fseries%3D330" title="Match Point - ColorBody™ Porcelain Tile | Daltile">
      <TargetSentence>Inspiring Ideas through Real Use Photo features &lt;b&gt;Match Point&lt;/b&gt; in Jet Black and   Pure White on the floor. As seen on Extreme Makeover Home Edition, Season 9.</TargetSentence>
    </match_point.n.16>
    <match_point.n.17 url="http://www.youtube.com/watch%3Fv%3DYY-vstEVfCQ" title="Match point - YouTube">
      <TargetSentence>Mar 12, 2007 &lt;b&gt;...&lt;/b&gt; Sign in with your YouTube Account (YouTube, Google+, Gmail, Orkut, Picasa, or   Chrome) to add misshelo&amp;#39;s video to your playlist. Sign in &lt;b&gt;...&lt;/b&gt;</TargetSentence>
    </match_point.n.17>
    <match_point.n.18 url="http://movies.tvguide.com/match-point/198463" title="Match Point Trailer, Reviews and Schedule for ... - TV Guide.com">
      <TargetSentence>&lt;b&gt;Match Point&lt;/b&gt; Trailer, Reviews, Schedule, Photos and &lt;b&gt;Match Point&lt;/b&gt; Cast on   TVGuide.com.</TargetSentence>
    </match_point.n.18>
    <match_point.n.19 url="http://en.wiktionary.org/wiki/match_point" title="match point - Wiktionary">
      <TargetSentence>&lt;b&gt;match point&lt;/b&gt; (plural match points). (sports, tennis) A state in a game where a   player can win the entire match by winning the next point. Often used in tennis.</TargetSentence>
    </match_point.n.19>
    <match_point.n.20 url="http://www.fandango.com/matchpoint_86286/movieoverview" title="Match Point Movie Tickets, Reviews, and Photos - Fandango.com">
      <TargetSentence>Get the &lt;b&gt;Match Point&lt;/b&gt; plot, movie times, movie trailers, movie tickets, cast photos,   and more on Fandango.com.</TargetSentence>
    </match_point.n.20>
    <match_point.n.21 url="http://www.merriam-webster.com/dictionary/match%2520point" title="Match point - Merriam-Webster Online">
      <TargetSentence>a situation (as in tennis) in which one player or side will win the match by winning   the next point; also : the point itself. See &lt;b&gt;match point&lt;/b&gt; defined for &lt;b&gt;...&lt;/b&gt;</TargetSentence>
    </match_point.n.21>
    <match_point.n.22 url="http://movies.netflix.com/WiMovie/Match_Point/70035180%3Flocale%3Den-US" title="Match Point | Netflix">
      <TargetSentence>&lt;b&gt;Match Point&lt;/b&gt; - In this suspenseful drama from writer-director Woody Allen, an   ambitious tennis pro gets mixed up with the darker side of high society -- and   when &lt;b&gt;...&lt;/b&gt;</TargetSentence>
    </match_point.n.22>
    <match_point.n.23 url="http://tvtropes.org/pmwiki/pmwiki.php/Main/MatchPoint" title="Match Point - Television Tropes &amp;amp; Idioms">
      <TargetSentence>&lt;b&gt;Match Point&lt;/b&gt; is a 2005 drama, written and directed by Woody Allen, and starring   Jonathan Rhys Meyers and Scarlett Johansson, as well as Emily Mortimer, Bryan &lt;b&gt;...&lt;/b&gt;</TargetSentence>
    </match_point.n.23>
    <match_point.n.24 url="http://templeterrace.patch.com/listings/match-point-seafood-bar-grill" title="Match Point Seafood Bar &amp;amp; Grill - Temple Terrace, FL Patch">
      <TargetSentence>&lt;b&gt;Match Point&lt;/b&gt; Seafood Bar &amp;amp; Grill offers a sports bar environment. The menu   includes seafood, barbeque and sandwiches. &lt;b&gt;Match Point&lt;/b&gt; has several   televisions &lt;b&gt;...&lt;/b&gt;</TargetSentence>
    </match_point.n.24>
    <match_point.n.25 url="http://usmatchpoint.com/" title="Match Point">
      <TargetSentence>FROM THE &lt;b&gt;MATCH POINT&lt;/b&gt; FAMILY. UPCOMING SHOW!! MODA MANHATTAN.   JAVIT CENTER. JAN 06 (SUN) - JAN 08 (TUES), 2012. BOOTH # 1738 &lt;b&gt;...&lt;/b&gt;</TargetSentence>
    </match_point.n.25>
    <match_point.n.26 url="http://www.tumblr.com/tagged/match%2520point" title="match point | Tumblr">
      <TargetSentence>#ghost world · #he&amp;#39;s just not that into you · #iron man 2 · #lost in translation · #  scarlett johansson · #the avengers · #the other boleyn girl · #scarlett johansson &lt;b&gt;...&lt;/b&gt;</TargetSentence>
    </match_point.n.26>
    <match_point.n.27 url="http://www.imdb.com/video/screenplay/vi1286340889/" title="Match Point Trailer - IMDb">
      <TargetSentence>Keep track of &amp;quot;Match Point&amp;quot;. Title: Match Point Trailer. Description: At a turning   point in his life, a former tennis pro falls for a femme-fatal type who happens to be &lt;b&gt;...&lt;/b&gt;</TargetSentence>
    </match_point.n.27>
    <match_point.n.28 url="http://wiki.teamliquid.net/starcraft2/ICCup_Match_Point" title="Match Point - Liquipedia - The StarCraft II Encyclopedia">
      <TargetSentence>Dec 19, 2012 &lt;b&gt;...&lt;/b&gt; &lt;b&gt;Match Point&lt;/b&gt;-1 12.jpg. [edit] Map Description. &lt;b&gt;Match Point&lt;/b&gt; is a conversion of the   Brood War Proleague map &lt;b&gt;Match Point&lt;/b&gt;. [edit] Notable Features &lt;b&gt;...&lt;/b&gt;</TargetSentence>
    </match_point.n.28>
    <match_point.n.29 url="http://wiki.teamliquid.net/starcraft/Match_Point" title="Match Point - Liquipedia Starcraft Wiki">
      <TargetSentence>Dec 18, 2012 &lt;b&gt;...&lt;/b&gt; &lt;b&gt;Match Point&lt;/b&gt; is the weirdest map for Protoss – they dominate Zerg and get   stomped by Terran. In TvP, the way the expansions pan out is Terran &lt;b&gt;...&lt;/b&gt;</TargetSentence>
    </match_point.n.29>
    <match_point.n.30 url="http://www.match-point-online.com/" title="Matchpoint -">
      <TargetSentence>Come visit us at &lt;b&gt;Matchpoint&lt;/b&gt;, where your new home is only minutes away from   shopping, dining, entertainment and we are conveniently located to major &lt;b&gt;...&lt;/b&gt;</TargetSentence>
    </match_point.n.30>
    <match_point.n.31 url="http://www.guardian.co.uk/film/movie/110136/match.point" title="Match Point | Film | The Guardian">
      <TargetSentence>&lt;b&gt;Match Point&lt;/b&gt;. &lt;b&gt;...&lt;/b&gt; Emily Mortimer and Jonathan Rhys-Meyers in &lt;b&gt;Match Point&lt;/b&gt;. Details  : 2005, Rest of the world, UK, USA, Cert 12A, 124 minutes mins, Comedy &lt;b&gt;...&lt;/b&gt;</TargetSentence>
    </match_point.n.31>
    <match_point.n.32 url="http://www.apartments.com/Virginia/Richmond/Match-Point/398130" title="Match Point Apartments in Richmond, VA | Apartments.com">
      <TargetSentence>Getting everything you want in an affordable apartment and staying within your   budget is possible at &lt;b&gt;Match Point&lt;/b&gt; Apartments apartments in Richmond, VA.</TargetSentence>
    </match_point.n.32>
    <match_point.n.33 url="http://www.rolandberger.com/expertise/functional_issues/match_point_management/" title="Match Point Management | Functional know-how | Expertise ...">
      <TargetSentence>&lt;b&gt;Match Point&lt;/b&gt; Management is a unique approach which brings together Roland   Berger&amp;#39;s expertise on customer-centric go-to-market strategies as well as sales &lt;b&gt;...&lt;/b&gt;</TargetSentence>
    </match_point.n.33>
    <match_point.n.34 url="http://www.teamliquid.net/tlpd/korean/maps/235_Match%2520Point" title="TLPD - BW Korean - Map Information - Match Point">
      <TargetSentence>TLPD - BW Korean - Map Information - &lt;b&gt;Match Point&lt;/b&gt; &lt;b&gt;...&lt;/b&gt; &lt;b&gt;Match Point&lt;/b&gt; [ Download ]   매치포인트. Size: 96x128. Spots: 1, 7. Tileset: Space Platform Games played: &lt;b&gt;...&lt;/b&gt;</TargetSentence>
    </match_point.n.34>
    <match_point.n.35 url="http://matchpointpro.com/" title="— Match Point Productions">
      <TargetSentence>Welcome to &lt;b&gt;Match Point&lt;/b&gt; Productions. We are a friendly media production house   based out of Austin, TX. Our goal is to bring you high value, high-end media &lt;b&gt;...&lt;/b&gt;</TargetSentence>
    </match_point.n.35>
    <match_point.n.36 url="http://sbtennispatrons.org/%3Fpage_id%3D1155" title="Match Point | Santa Barbara Tennis Patrons">
      <TargetSentence>&lt;b&gt;Match Point&lt;/b&gt; provides after school educational services and tennis instruction for “  at risk” youth in the 4th, 5th, and 6th grades who primarily attend Franklin and &lt;b&gt;...&lt;/b&gt;</TargetSentence>
    </match_point.n.36>
    <match_point.n.37 url="http://www.youtube.com/watch%3Fv%3DvVjfW-P5yZY" title="Kiss in the Rain - Match Point (5/8) Movie CLIP (2005) HD - YouTube">
      <TargetSentence>May 21, 2012 &lt;b&gt;...&lt;/b&gt; &lt;b&gt;Match Point&lt;/b&gt; Movie Clip - watch all clips http://j.mp/J9cB95 click to subscribe http://  j.mp/sNDUs5 Nola (Scarlett Johansson) and Chris (Jonathan &lt;b&gt;...&lt;/b&gt;</TargetSentence>
    </match_point.n.37>
    <match_point.n.38 url="http://www.matchpoint-tennis.com/" title="Match Point Tennis Online - Florida&amp;#39;s Tennis Superstore">
      <TargetSentence>&lt;b&gt;Match Point&lt;/b&gt; Tennis is South Florida&amp;#39;s tennis superstore! We&amp;#39;re located on   Oakland Park Boulevard in Fort Lauderdale, just 30 minutes from Miami and   West &lt;b&gt;...&lt;/b&gt;</TargetSentence>
    </match_point.n.38>
    <match_point.n.39 url="http://www.moviefone.com/movie/match-point/23105/main" title="Match Point | Moviefone">
      <TargetSentence>&lt;b&gt;Match Point&lt;/b&gt; Movie - Starring Scarlett Johansson, Jonathan Rhys-Meyers, Emily   Mortimer, Matthew Goode - A clandestine love affair sends one man&amp;#39;s charmed &lt;b&gt;...&lt;/b&gt;</TargetSentence>
    </match_point.n.39>
    <match_point.n.40 url="http://www.everywoodyallenmovie.com/post/match-point/" title="Match Point | Every Woody Allen Movie">
      <TargetSentence>Apr 1, 2012 &lt;b&gt;...&lt;/b&gt; Woody Allen&amp;#39;s departure from New York results in a thriller that is sexy and smart,   although emotionally cold.</TargetSentence>
    </match_point.n.40>
    <match_point.n.41 url="http://www.blockbuster.com/browse/catalog/movieDetails/265099" title="Match Point DVD Rental, Rent Match Point Movie Online">
      <TargetSentence>Rent &lt;b&gt;Match Point&lt;/b&gt; DVD and over 100000 other movies at Blockbuster. Buy,   Download, or Rent &lt;b&gt;Match Point&lt;/b&gt; at Blockbuster today. Your source for &lt;b&gt;Match Point&lt;/b&gt; &lt;b&gt;...&lt;/b&gt;</TargetSentence>
    </match_point.n.41>
    <match_point.n.42 url="http://www.movie-locations.com/movies/m/matchpoint_01.html" title="Film locations for Match Point (2005)">
      <TargetSentence>Dec 9, 2012 &lt;b&gt;...&lt;/b&gt; Filming locations for Woody Allen&amp;#39;s &lt;b&gt;Match Point&lt;/b&gt; around London; including   Queen&amp;#39;s Club, Baron&amp;#39;s Court; the Royal Opera House, Covent &lt;b&gt;...&lt;/b&gt;</TargetSentence>
    </match_point.n.42>
    <match_point.n.43 url="http://worldfilm.about.com/od/k/fr/matchpoint.htm" title="Match Point - Woody Allen - Review">
      <TargetSentence>Every time Woody Allen releases a new film, it&amp;#39;s the same ritual. The advance   buzz tells us that this one marks his return to form! Don&amp;#39;t believe a word.</TargetSentence>
    </match_point.n.43>
    <match_point.n.44 url="http://www.metacritic.com/movie/match-point" title="Match Point Reviews, Ratings, Credits, and More - Metacritic">
      <TargetSentence>Dec 28, 2005 &lt;b&gt;...&lt;/b&gt; Metacritic Movie Reviews, &lt;b&gt;Match Point&lt;/b&gt;, &lt;b&gt;Match Point&lt;/b&gt; is a drama about ambition   and obsession, the seduction of wealth, and the often discordant &lt;b&gt;...&lt;/b&gt;</TargetSentence>
    </match_point.n.44>
    <match_point.n.45 url="http://matchpointprojects.com/" title="Match Point Projects">
      <TargetSentence>&lt;b&gt;Match Point&lt;/b&gt; Projects.</TargetSentence>
    </match_point.n.45>
    <match_point.n.46 url="http://match-point.livejournal.com/" title="Match Point">
      <TargetSentence>Since we haven&amp;#39;t had a post for nearly the last two years, I declare that &lt;b&gt;Match&lt;/b&gt;   &lt;b&gt;Point&lt;/b&gt; is officially closed. The journals and website will remain for the   entertainment &lt;b&gt;...&lt;/b&gt;</TargetSentence>
    </match_point.n.46>
    <match_point.n.47 url="http://www.youtube.com/watch%3Fv%3Drm17YtyyyjY" title="MATCH POINT SUBTITULADA AL ESPAÑOL - YouTube">
      <TargetSentence>Aug 21, 2012 &lt;b&gt;...&lt;/b&gt; &lt;b&gt;MATCH POINT&lt;/b&gt; PELICULA COMPLETA scarlett johanson, jonathan rhys meyers,   woody allen, emily mortimer, matthew goode, penelope wilton &lt;b&gt;...&lt;/b&gt;</TargetSentence>
    </match_point.n.47>
    <match_point.n.48 url="http://www.moviemistakes.com/film5452" title="Match Point movie mistakes, goofs and bloopers">
      <TargetSentence>Mistakes, goofs, trivia, quotes, trailers, pictures and more for &lt;b&gt;Match Point&lt;/b&gt;.</TargetSentence>
    </match_point.n.48>
    <match_point.n.49 url="http://www.facebook.com/pages/Match-Point/22380058368" title="Match Point | Facebook">
      <TargetSentence>Highlights, Highlights, Posts by Page, Posts by Others. Activity. December.   People Who Like This. 572. Recent Posts by Others on &lt;b&gt;Match Point&lt;/b&gt;See All &lt;b&gt;...&lt;/b&gt;</TargetSentence>
    </match_point.n.49>
    <match_point.n.50 url="http://www.starpulse.com/Movies/Match_Point/" title="Match Point Pictures, News, Reviews, Summary, Great Film ...">
      <TargetSentence>&lt;b&gt;Match Point&lt;/b&gt; Pictures, News, Reviews, Summary, Great Film Moments, Cast and   Crew, Videos.</TargetSentence>
    </match_point.n.50>
    <match_point.n.51 url="http://www.matchpointohio.com/" title="Match Point Ohio">
      <TargetSentence>MatchPointOhio celebrates the Ohio University women&amp;#39;s volleyball team. Over   the past decade, the Bobcats have been one of the most successful and &lt;b&gt;...&lt;/b&gt;</TargetSentence>
    </match_point.n.51>
    <match_point.n.52 url="http://www.matchpoint.co.uk/" title="Welcome to Match Point">
      <TargetSentence>Corporate entertainment to major sporting events, on-line booking form and   details of all events.</TargetSentence>
    </match_point.n.52>
    <match_point.n.53 url="http://www.pehub.com/169418/burkett-friedland-launch-match-point-partner/" title="Burkett, Friedland Launch Match Point Partners - peHUBpeHUB">
      <TargetSentence>Oct 12, 2012 &lt;b&gt;...&lt;/b&gt; Brad Burkett and J.D. Friedland have launched &lt;b&gt;Match Point&lt;/b&gt; Partners. New York-  based &lt;b&gt;Match Point&lt;/b&gt; is a strategy and financial advisory that &lt;b&gt;...&lt;/b&gt;</TargetSentence>
    </match_point.n.53>
    <match_point.n.54 url="http://www.yelp.com/biz/match-point-tampa" title="Match Point - Tampa, FL">
      <TargetSentence>Mar 15, 2011 &lt;b&gt;...&lt;/b&gt; 1 Review of &lt;b&gt;Match Point&lt;/b&gt; &amp;quot;I love the ribs! They&amp;#39;re fall off the bone delicious!!!&amp;quot;</TargetSentence>
    </match_point.n.54>
    <match_point.n.55 url="http://www.thenedpages.com/reviews/mtchpnt.html" title="Review: Match Point">
      <TargetSentence>The new film from Woody Allen is his best, most focused effort in years, a return to   subjects that have inspired and engaged him throughout his career.</TargetSentence>
    </match_point.n.55>
    <match_point.n.56 url="http://www.matchpointcoaching.com/" title="Home - Match Point">
      <TargetSentence>When I was first approached with the prospect of meeting with a career coach, I   have to admit I was quite nervous to discuss my future with someone I had never &lt;b&gt;...&lt;/b&gt;</TargetSentence>
    </match_point.n.56>
    <match_point.n.57 url="http://www.imdb.com/title/tt0416320/fullcredits" title="Match Point (2005) - Full cast and crew">
      <TargetSentence>IMDb &amp;gt; Match Point (2005) &amp;gt; Full cast and crew. Match Point · Own the rights?   Buy it at Amazon &lt;b&gt;...&lt;/b&gt; Cast (in credits order) complete, awaiting verification &lt;b&gt;...&lt;/b&gt;</TargetSentence>
    </match_point.n.57>
    <match_point.n.58 url="http://www.apartmentguide.com/apartments/Virginia/Richmond/Match-Point-Apartments/9303/" title="Match Point Apartments - Richmond, VA 23225 | Apartments for Rent">
      <TargetSentence>Check availability and view photos, apartment amenities and community features   for &lt;b&gt;Match Point&lt;/b&gt; apartments in Richmond, Virginia.</TargetSentence>
    </match_point.n.58>
    <match_point.n.59 url="http://www.themoviedb.org/movie/116-match-point" title="Match Point — The Movie Database">
      <TargetSentence>&lt;b&gt;Match Point&lt;/b&gt; is Woody Allen&amp;#39;s satire of the British High Society and the ambition of   a young tennis instructor to enter into it. Yet when he must decide between two &lt;b&gt;...&lt;/b&gt;</TargetSentence>
    </match_point.n.59>
    <match_point.n.60 url="http://sentence.yourdictionary.com/match-point" title="match point - Sentence Examples - YourDictionary">
      <TargetSentence>How to use &lt;b&gt;match point&lt;/b&gt; in a sentence. Example sentences with the word &lt;b&gt;match&lt;/b&gt;   &lt;b&gt;point&lt;/b&gt;. &lt;b&gt;match point&lt;/b&gt; example sentences.</TargetSentence>
    </match_point.n.60>
    <match_point.n.61 url="http://www.matchpointlakeville.com/" title="Match Point Tennis, Lakeville, MN">
      <TargetSentence>&lt;b&gt;Match Point&lt;/b&gt; Tennis Center in Lakeville, MN offers state of the art tennis facilities   and tennis lessons to Minnesotans.</TargetSentence>
    </match_point.n.61>
    <match_point.n.62 url="http://www.matchpointaus.com/" title="Welcome to Match Point">
      <TargetSentence>&lt;b&gt;MatchPoint&lt;/b&gt; is a corporate hospitality specialist. &lt;b&gt;MatchPoint&lt;/b&gt; are dedicated to   providing the very best in corporate entertainment.</TargetSentence>
    </match_point.n.62>
    <match_point.n.63 url="http://www.amazon.com/Match-Point-Lauren-Holbrook-Series/dp/1600063098" title="Match Point (Lauren Holbrook Series, Book 3): Erynn Mangum ...">
      <TargetSentence>&lt;b&gt;Match Point&lt;/b&gt; (Lauren Holbrook Series, Book 3) [Erynn Mangum] on Amazon.com.   *FREE* super saver shipping on qualifying offers. Matchmaker Lauren &lt;b&gt;...&lt;/b&gt;</TargetSentence>
    </match_point.n.63>
    <match_point.n.64 url="http://www.moviemistakes.com/film5452/trailer" title="Match Point movie trailer and videos">
      <TargetSentence>&lt;b&gt;Match Point&lt;/b&gt; movie trailer, plus mistakes, quotes, trivia and pictures.</TargetSentence>
    </match_point.n.64>
  </match_point.n.test>
</dataSet>
